MANIFEST.in
README.rst
setup.py
pysokoban/__init__.py
pysokoban/sokoban.py
pysokoban.egg-info/PKG-INFO
pysokoban.egg-info/SOURCES.txt
pysokoban.egg-info/dependency_links.txt
pysokoban.egg-info/entry_points.txt
pysokoban.egg-info/top_level.txt
pysokoban/images/__init__.py
pysokoban/images/crate-in-hole.gif
pysokoban/images/crate.gif
pysokoban/images/hole.gif
pysokoban/images/player-in-hole.gif
pysokoban/images/player.gif
pysokoban/images/wall.gif
pysokoban/levels/Jordi-Domenech/Level1.skb
pysokoban/levels/Jordi-Domenech/Level2.skb
pysokoban/levels/Jordi-Domenech/Level3.skb
pysokoban/levels/Jordi-Domenech/Level4.skb
pysokoban/levels/Jordi-Domenech/Level5.skb
pysokoban/levels/Risto-Stevcev/Level1.skb