Metadata-Version: 1.1
Name: pysokoban
Version: 1.1
Summary: A highly customizable sokoban implementation using Python's tkinter.
Home-page: https://github.com/Risto-Stevcev/pysokoban
Author: Risto Stevcev
Author-email: risto1@gmail.com
License: BSD
Platform: UNKNOWN
Classifier: Development Status :: 4 - Beta
Classifier: Environment :: X11 Applications
Classifier: Intended Audience :: End Users/Desktop
Classifier: License :: OSI Approved :: BSD License
Classifier: Natural Language :: English
Classifier: Operating System :: OS Independent
Classifier: Programming Language :: Python :: 2
Classifier: Topic :: Games/Entertainment :: Puzzle Games
